{
  "imageData": null,
  "fillColor": [
    255,
    0,
    0,
    128
  ],
  "lineColor": [
    0,
    255,
    0,
    128
  ],
  "imagePath": "118.jpg",
  "imageHeight": 1900,
  "imageWidth": 1200,
  "shapes": [
    {
      "line_color": null,
      "fill_color": null,
      "shape_type": "rectangle",
      "label": "isolated_expression",
      "group_id": 0,
      "points": [
        [
          153,
          883
        ],
        [
          394.86,
          927.26
        ]
      ]
    },
    {
      "line_color": null,
      "fill_color": null,
      "shape_type": "rectangle",
      "label": "isolated_expression",
      "group_id": 1,
      "points": [
        [
          147,
          1016
        ],
        [
          450.81,
          1061.67
        ]
      ]
    },
    {
      "line_color": null,
      "fill_color": null,
      "shape_type": "rectangle",
      "label": "isolated_expression",
      "group_id": 2,
      "points": [
        [
          141,
          781
        ],
        [
          514.83,
          820.19
        ]
      ]
    },
    {
      "line_color": null,
      "fill_color": null,
      "shape_type": "rectangle",
      "label": "isolated_expression",
      "group_id": 3,
      "points": [
        [
          152,
          1708
        ],
        [
          1084.18,
          1758.92
        ]
      ]
    },
    {
      "line_color": null,
      "fill_color": null,
      "shape_type": "rectangle",
      "label": "isolated_expression",
      "group_id": 4,
      "points": [
        [
          138,
          259
        ],
        [
          467.24,
          301.67
        ]
      ]
    },
    {
      "line_color": null,
      "fill_color": null,
      "shape_type": "rectangle",
      "label": "isolated_expression",
      "group_id": 5,
      "points": [
        [
          138,
          544
        ],
        [
          641.73,
          587.87
        ]
      ]
    },
    {
      "line_color": null,
      "fill_color": null,
      "shape_type": "rectangle",
      "label": "isolated_expression",
      "group_id": 6,
      "points": [
        [
          151,
          638
        ],
        [
          1084.83,
          693.55
        ]
      ]
    },
    {
      "line_color": null,
      "fill_color": null,
      "shape_type": "rectangle",
      "label": "isolated_expression",
      "group_id": 7,
      "points": [
        [
          145,
          1321
        ],
        [
          1084.9,
          1378.52
        ]
      ]
    },
    {
      "line_color": null,
      "fill_color": null,
      "shape_type": "rectangle",
      "label": "isolated_expression",
      "group_id": 8,
      "points": [
        [
          160,
          1433
        ],
        [
          298.23,
          1492.41
        ]
      ]
    },
    {
      "line_color": null,
      "fill_color": null,
      "shape_type": "rectangle",
      "label": "isolated_expression",
      "group_id": 9,
      "points": [
        [
          151,
          1547
        ],
        [
          269.21,
          1598.28
        ]
      ]
    }
  ]
}