{
  "imageData": null,
  "fillColor": [
    255,
    0,
    0,
    128
  ],
  "lineColor": [
    0,
    255,
    0,
    128
  ],
  "imagePath": "129.jpg",
  "imageHeight": 1906,
  "imageWidth": 1209,
  "shapes": [
    {
      "line_color": null,
      "fill_color": null,
      "shape_type": "rectangle",
      "label": "isolated_expression",
      "group_id": 0,
      "points": [
        [
          160,
          1082
        ],
        [
          663.96,
          1352.39
        ]
      ]
    },
    {
      "line_color": null,
      "fill_color": null,
      "shape_type": "rectangle",
      "label": "isolated_expression",
      "group_id": 1,
      "points": [
        [
          155,
          766
        ],
        [
          1089.62,
          808.65
        ]
      ]
    },
    {
      "line_color": null,
      "fill_color": null,
      "shape_type": "rectangle",
      "label": "isolated_expression",
      "group_id": 2,
      "points": [
        [
          162,
          1710
        ],
        [
          1090.92,
          1758.39
        ]
      ]
    },
    {
      "line_color": null,
      "fill_color": null,
      "shape_type": "rectangle",
      "label": "isolated_expression",
      "group_id": 3,
      "points": [
        [
          170,
          923
        ],
        [
          409.21,
          966.82
        ]
      ]
    },
    {
      "line_color": null,
      "fill_color": null,
      "shape_type": "rectangle",
      "label": "isolated_expression",
      "group_id": 4,
      "points": [
        [
          156,
          1412
        ],
        [
          626.31,
          1557.02
        ]
      ]
    },
    {
      "line_color": null,
      "fill_color": null,
      "shape_type": "rectangle",
      "label": "isolated_expression",
      "group_id": 5,
      "points": [
        [
          167,
          874
        ],
        [
          388.16,
          914.78
        ]
      ]
    },
    {
      "line_color": null,
      "fill_color": null,
      "shape_type": "rectangle",
      "label": "isolated_expression",
      "group_id": 6,
      "points": [
        [
          156,
          324
        ],
        [
          1090.71,
          370.75
        ]
      ]
    },
    {
      "line_color": null,
      "fill_color": null,
      "shape_type": "rectangle",
      "label": "isolated_expression",
      "group_id": 7,
      "points": [
        [
          151,
          596
        ],
        [
          1086.03,
          647.39
        ]
      ]
    }
  ]
}