{
  "imageData": null,
  "fillColor": [
    255,
    0,
    0,
    128
  ],
  "lineColor": [
    0,
    255,
    0,
    128
  ],
  "imagePath": "23.jpg",
  "imageHeight": 1930,
  "imageWidth": 1260,
  "shapes": [
    {
      "line_color": null,
      "fill_color": null,
      "shape_type": "rectangle",
      "label": "isolated_expression",
      "group_id": 0,
      "points": [
        [
          397,
          956
        ],
        [
          696.08,
          1005.7
        ]
      ]
    },
    {
      "line_color": null,
      "fill_color": null,
      "shape_type": "rectangle",
      "label": "isolated_expression",
      "group_id": 1,
      "points": [
        [
          439,
          1301
        ],
        [
          663.74,
          1347.14
        ]
      ]
    },
    {
      "line_color": null,
      "fill_color": null,
      "shape_type": "rectangle",
      "label": "isolated_expression",
      "group_id": 2,
      "points": [
        [
          349,
          1440
        ],
        [
          750,
          1485.47
        ]
      ]
    }
  ]
}