{
  "imageData": null,
  "fillColor": [
    255,
    0,
    0,
    128
  ],
  "lineColor": [
    0,
    255,
    0,
    128
  ],
  "imagePath": "505.jpg",
  "imageHeight": 2339,
  "imageWidth": 1653,
  "shapes": [
    {
      "line_color": null,
      "fill_color": null,
      "shape_type": "rectangle",
      "label": "isolated_expression",
      "group_id": 0,
      "points": [
        [
          354,
          1021
        ],
        [
          948.61,
          1071.9
        ]
      ]
    },
    {
      "line_color": null,
      "fill_color": null,
      "shape_type": "rectangle",
      "label": "isolated_expression",
      "group_id": 1,
      "points": [
        [
          339,
          392
        ],
        [
          968.49,
          432.37
        ]
      ]
    }
  ]
}