{
  "imageData": null,
  "fillColor": [
    255,
    0,
    0,
    128
  ],
  "lineColor": [
    0,
    255,
    0,
    128
  ],
  "imagePath": "589.jpg",
  "imageHeight": 2314,
  "imageWidth": 1725,
  "shapes": [
    {
      "line_color": null,
      "fill_color": null,
      "shape_type": "rectangle",
      "label": "isolated_expression",
      "group_id": 0,
      "points": [
        [
          606,
          1033
        ],
        [
          1414.84,
          1127.47
        ]
      ]
    },
    {
      "line_color": null,
      "fill_color": null,
      "shape_type": "rectangle",
      "label": "isolated_expression",
      "group_id": 1,
      "points": [
        [
          616,
          1324
        ],
        [
          1106.08,
          1411.97
        ]
      ]
    },
    {
      "line_color": null,
      "fill_color": null,
      "shape_type": "rectangle",
      "label": "isolated_expression",
      "group_id": 2,
      "points": [
        [
          661,
          1429
        ],
        [
          1062.24,
          1509.53
        ]
      ]
    },
    {
      "line_color": null,
      "fill_color": null,
      "shape_type": "rectangle",
      "label": "isolated_expression",
      "group_id": 3,
      "points": [
        [
          775,
          1773
        ],
        [
          958.63,
          1819.12
        ]
      ]
    },
    {
      "line_color": null,
      "fill_color": null,
      "shape_type": "rectangle",
      "label": "isolated_expression",
      "group_id": 4,
      "points": [
        [
          688,
          1879
        ],
        [
          1047.79,
          1939.36
        ]
      ]
    }
  ]
}