{
  "imageData": null,
  "fillColor": [
    255,
    0,
    0,
    128
  ],
  "lineColor": [
    0,
    255,
    0,
    128
  ],
  "imagePath": "615.jpg",
  "imageHeight": 1900,
  "imageWidth": 1200,
  "shapes": [
    {
      "line_color": null,
      "fill_color": null,
      "shape_type": "rectangle",
      "label": "isolated_expression",
      "group_id": 0,
      "points": [
        [
          454,
          477
        ],
        [
          1089.67,
          566.33
        ]
      ]
    },
    {
      "line_color": null,
      "fill_color": null,
      "shape_type": "rectangle",
      "label": "isolated_expression",
      "group_id": 1,
      "points": [
        [
          526,
          603
        ],
        [
          1093.04,
          653.4
        ]
      ]
    },
    {
      "line_color": null,
      "fill_color": null,
      "shape_type": "rectangle",
      "label": "isolated_expression",
      "group_id": 2,
      "points": [
        [
          335,
          944
        ],
        [
          1094.95,
          993.29
        ]
      ]
    },
    {
      "line_color": null,
      "fill_color": null,
      "shape_type": "rectangle",
      "label": "isolated_expression",
      "group_id": 3,
      "points": [
        [
          432,
          1081
        ],
        [
          1092.89,
          1132.47
        ]
      ]
    },
    {
      "line_color": null,
      "fill_color": null,
      "shape_type": "rectangle",
      "label": "isolated_expression",
      "group_id": 4,
      "points": [
        [
          413,
          1345
        ],
        [
          789.88,
          1396.68
        ]
      ]
    },
    {
      "line_color": null,
      "fill_color": null,
      "shape_type": "rectangle",
      "label": "isolated_expression",
      "group_id": 5,
      "points": [
        [
          454,
          1467
        ],
        [
          749.9,
          1555.05
        ]
      ]
    },
    {
      "line_color": null,
      "fill_color": null,
      "shape_type": "rectangle",
      "label": "isolated_expression",
      "group_id": 6,
      "points": [
        [
          479,
          1611
        ],
        [
          1095.65,
          1699.05
        ]
      ]
    }
  ]
}