{
  "imageData": null,
  "fillColor": [
    255,
    0,
    0,
    128
  ],
  "lineColor": [
    0,
    255,
    0,
    128
  ],
  "imagePath": "694.jpg",
  "imageHeight": 1890,
  "imageWidth": 1260,
  "shapes": [
    {
      "line_color": null,
      "fill_color": null,
      "shape_type": "rectangle",
      "label": "isolated_expression",
      "group_id": 0,
      "points": [
        [
          155,
          1315
        ],
        [
          833.24,
          1401.38
        ]
      ]
    },
    {
      "line_color": null,
      "fill_color": null,
      "shape_type": "rectangle",
      "label": "isolated_expression",
      "group_id": 1,
      "points": [
        [
          157,
          1488
        ],
        [
          769.29,
          1569.64
        ]
      ]
    }
  ]
}