{
  "imageData": null,
  "fillColor": [
    255,
    0,
    0,
    128
  ],
  "lineColor": [
    0,
    255,
    0,
    128
  ],
  "imagePath": "736.jpg",
  "imageHeight": 2071,
  "imageWidth": 1462,
  "shapes": [
    {
      "line_color": null,
      "fill_color": null,
      "shape_type": "rectangle",
      "label": "isolated_expression",
      "group_id": 0,
      "points": [
        [
          526,
          302
        ],
        [
          941.65,
          375.57
        ]
      ]
    },
    {
      "line_color": null,
      "fill_color": null,
      "shape_type": "rectangle",
      "label": "isolated_expression",
      "group_id": 1,
      "points": [
        [
          500,
          466
        ],
        [
          974.47,
          539.76
        ]
      ]
    },
    {
      "line_color": null,
      "fill_color": null,
      "shape_type": "rectangle",
      "label": "isolated_expression",
      "group_id": 2,
      "points": [
        [
          433,
          595
        ],
        [
          1032.47,
          668.03
        ]
      ]
    },
    {
      "line_color": null,
      "fill_color": null,
      "shape_type": "rectangle",
      "label": "isolated_expression",
      "group_id": 3,
      "points": [
        [
          438,
          717
        ],
        [
          1030.75,
          794.9
        ]
      ]
    },
    {
      "line_color": null,
      "fill_color": null,
      "shape_type": "rectangle",
      "label": "isolated_expression",
      "group_id": 4,
      "points": [
        [
          557,
          843
        ],
        [
          921.34,
          906.82
        ]
      ]
    },
    {
      "line_color": null,
      "fill_color": null,
      "shape_type": "rectangle",
      "label": "isolated_expression",
      "group_id": 5,
      "points": [
        [
          559,
          952
        ],
        [
          917.15,
          1011.13
        ]
      ]
    },
    {
      "line_color": null,
      "fill_color": null,
      "shape_type": "rectangle",
      "label": "isolated_expression",
      "group_id": 6,
      "points": [
        [
          509,
          1056
        ],
        [
          970.71,
          1119.62
        ]
      ]
    },
    {
      "line_color": null,
      "fill_color": null,
      "shape_type": "rectangle",
      "label": "isolated_expression",
      "group_id": 7,
      "points": [
        [
          510,
          1169
        ],
        [
          965.52,
          1241.1
        ]
      ]
    },
    {
      "line_color": null,
      "fill_color": null,
      "shape_type": "rectangle",
      "label": "isolated_expression",
      "group_id": 8,
      "points": [
        [
          433,
          1331
        ],
        [
          1041.88,
          1410.37
        ]
      ]
    }
  ]
}